[
    {
        "timestamp": "2026-03-28T08:07:02.920685",
        "action_type": "claim_task",
        "actor": "ai_employee",
        "target": "FILE_test_task_003.txt_20260328073205.md",
        "parameters": {
            "task": "FILE_test_task_003.txt_20260328073205.md",
            "is_email": false,
            "is_whatsapp": false
        },
        "approval_status": "auto",
        "approved_by": "system",
        "result": "success"
    }
]{"timestamp": "2026-03-28T03:07:08.504571+00:00", "action_type": "whatsapp_send_failed", "actor": "local", "target": "APPROVE_REPLY_WHATSAPP_OWNER_20260328073527.md", "parameters": {"error": "approval missing 'recipient' or 'message_body'"}, "approval_status": "auto", "approved_by": "system", "result": "error"}
{"timestamp": "2026-03-28T03:07:11.907984+00:00", "action_type": "whatsapp_send_failed", "actor": "local", "target": "APPROVE_REPLY_WHATSAPP_OWNER_20260328075427.md", "parameters": {"error": "approval missing 'recipient' or 'message_body'"}, "approval_status": "auto", "approved_by": "system", "result": "error"}
{"timestamp": "2026-03-28T03:07:25.101827+00:00", "action_type": "whatsapp_send_failed", "actor": "local", "target": "APPROVE_REPLY_WHATSAPP_OWNER_20260328073527.md", "parameters": {"error": "approval missing 'recipient' or 'message_body'"}, "approval_status": "auto", "approved_by": "system", "result": "error"}
